yaz/loader.py
yaz/error.py
yaz/main.py
yaz/log.py
yaz/parser.py
yaz/tester.py
yaz/__init__.py
yaz/plugin.py
yaz/version.py
yaz/task.py
yaz/decorator.py
yaz-1.1.2.dist-info/WHEEL
yaz-1.1.2.dist-info/RECORD
yaz-1.1.2.dist-info/METADATA
yaz-1.1.2.dist-info/top_level.txt
yaz-1.1.2.dist-info/DESCRIPTION.rst
yaz-1.1.2.dist-info/metadata.json
