Metadata-Version: 2.0
Name: yaz
Version: 1.1.2
Summary: A scripting tool
Home-page: https://github.com/yaz/yaz
Author: Boudewijn Schoon
Author-email: yaz@frayja.com
License: MIT
Platform: UNKNOWN
Classifier: Development Status :: 5 - Production/Stable
Classifier: Environment :: Console
Classifier: License :: OSI Approved :: MIT License
Classifier: Programming Language :: Python :: 3.5
Classifier: Programming Language :: Python :: 3.6
